README.md
lyricscorpora.py
setup.cfg
setup.py
lyricscorpora.egg-info/PKG-INFO
lyricscorpora.egg-info/SOURCES.txt
lyricscorpora.egg-info/dependency_links.txt
lyricscorpora.egg-info/entry_points.txt
lyricscorpora.egg-info/not-zip-safe
lyricscorpora.egg-info/requires.txt
lyricscorpora.egg-info/top_level.txt