Metadata-Version: 1.1
Name: lyricscorpora
Version: 0.2.0
Summary: Lyrics API
Home-page: https://github.com/edwardseley/lyrics-corpora
Author: Edward Seley
Author-email: edwardseley@gmail.com
License: No license
Keywords: lyrics LyricWikia music billboard songs scrape
Platform: UNKNOWN
Classifier: Programming Language :: Python :: 2
Classifier: Programming Language :: Python :: 3
Classifier: License :: OSI Approved :: BSD License
Classifier: Development Status :: 4 - Beta
Classifier: Topic :: Multimedia :: Sound/Audio
Classifier: Natural Language :: English
